pyimaz/__init__.py
pyimaz/_pyimaz.py
pyimaz/imaz.py
pyimaz/_ext/_data/Imaz pressure.txt
pyimaz/_ext/_data/chapman.txt
pyimaz/_ext/_data/data biases.txt
pyimaz/_ext/_data/data weights.txt
pyimaz/_ext/_data/nighttruequiet.txt
pyimaz/_ext/_data/press_60deg.txt
pyimaz/_ext/_data/press_70deg.txt
pyimaz-0.0.8b11.dist-info/LICENSE.txt
pyimaz-0.0.8b11.dist-info/METADATA
pyimaz-0.0.8b11.dist-info/WHEEL
pyimaz-0.0.8b11.dist-info/top_level.txt
pyimaz-0.0.8b11.dist-info/RECORD
