Metadata-Version: 2.1
Name: pyimaz
Version: 0.0.8b11
Summary: pyIMAZ is a Python3 implementation of the  a semi-empirical IMAZ model of the auroral Earth's ionosphere D-Region.
Home-page: https://gitlab.com/zolotov/pyimaz
Author: Denis Sakaev, Oleg Zolotov
Author-email: denissackaev@yandex.ru
License: Apache Software License
Keywords: lower ionosphere of the Earth,D-region,D-layer,model,FIRI
Platform: UNKNOWN
Classifier: Development Status :: 2 - Pre-Alpha
Classifier: Intended Audience :: Science/Research
Classifier: Topic :: Scientific/Engineering :: Physics
Classifier: License :: OSI Approved :: Apache Software License
Classifier: Programming Language :: Python :: 3
Classifier: Programming Language :: Python :: 3.6
Classifier: Programming Language :: Python :: 3.7
Classifier: Programming Language :: Python :: 3.8
Classifier: Programming Language :: Python :: 3.9
Classifier: Programming Language :: Python :: 3 :: Only
License-File: LICENSE.txt
Requires-Dist: numpy
